setup.py
visdom_pooled/__init__.py
visdom_pooled.egg-info/PKG-INFO
visdom_pooled.egg-info/SOURCES.txt
visdom_pooled.egg-info/dependency_links.txt
visdom_pooled.egg-info/requires.txt
visdom_pooled.egg-info/top_level.txt