Metadata-Version: 1.1
Name: visdom-pooled
Version: 1.0
Summary: Slightly More Efficient Visdom Wrapper
Home-page: https://github.com/kaniblu/visdom-pooled
Author: Kang Min Yoo
Author-email: k@nib.lu
License: MIT
Keywords: visdom deeplearning visualization pooled
Platform: UNKNOWN
Classifier: Development Status :: 5 - Production/Stable
Classifier: Intended Audience :: Developers
Classifier: Programming Language :: Python :: 3
